inframe/__init__.py
inframe/query.py
inframe/recorder.py
inframe/_src/video_stream.cpython-311-darwin.so
inframe/legacy/__init__.py
inframe/legacy/query.py
inframe/legacy/recorder.py
inframe/legacy/_src/context_integrator.cpython-311-darwin.so
inframe/legacy/_src/context_querier.cpython-311-darwin.so
inframe/legacy/_src/tldw_utils.cpython-311-darwin.so
inframe/legacy/_src/transcription_pipeline.cpython-311-darwin.so
inframe/legacy/_src/video_stream.cpython-311-darwin.so
inframe/legacy/examples/simple_agent.py
inframe-0.2.10.dist-info/licenses/LICENSE
inframe-0.2.10.dist-info/METADATA
inframe-0.2.10.dist-info/WHEEL
inframe-0.2.10.dist-info/top_level.txt
inframe-0.2.10.dist-info/RECORD
