Metadata-Version: 2.4
Name: inframe
Version: 0.2.10
Summary: Screen Context Recording and Querying SDK
Author-email: Inframe <bendgeist99@gmail.com>
License: Proprietary
Project-URL: Source, https://github.com/BenDGeist/inframe-public
Project-URL: Documentation, https://github.com/BenDGeist/inframe-public
Keywords: screen recording,context,AI,transcription,video processing
Classifier: Development Status :: 3 - Alpha
Classifier: Intended Audience :: Developers
Classifier: Operating System :: MacOS :: MacOS X
Classifier: Programming Language :: Python :: 3
Classifier: Programming Language :: Python :: 3.8
Classifier: Programming Language :: Python :: 3.9
Classifier: Programming Language :: Python :: 3.10
Classifier: Programming Language :: Python :: 3.11
Requires-Python: >=3.8
License-File: LICENSE
Requires-Dist: mss>=9.0.0
Requires-Dist: numpy<3.0.0,>=1.21.0
Requires-Dist: httpx>=0.24.0
Requires-Dist: pyobjc-core>=9.0; platform_system == "Darwin"
Requires-Dist: pyobjc-framework-Cocoa>=9.0; platform_system == "Darwin"
Requires-Dist: pyobjc-framework-AVFoundation>=9.0; platform_system == "Darwin"
Requires-Dist: pyobjc-framework-Quartz>=9.0; platform_system == "Darwin"
Requires-Dist: pyobjc-framework-ScreenCaptureKit>=9.0; platform_system == "Darwin"
Provides-Extra: dev
Requires-Dist: pytest>=6.0; extra == "dev"
Requires-Dist: pytest-asyncio>=0.21.0; extra == "dev"
Requires-Dist: black>=22.0; extra == "dev"
Requires-Dist: flake8>=4.0; extra == "dev"
Requires-Dist: python-dotenv>=1.0.0; extra == "dev"
Requires-Dist: PyJWT[crypto]; extra == "dev"
Requires-Dist: build; extra == "dev"
Requires-Dist: wheel; extra == "dev"
Requires-Dist: setuptools>=61.0; extra == "dev"
Requires-Dist: toml; extra == "dev"
Requires-Dist: Cython>=3.0.0; extra == "dev"
Provides-Extra: deploy
Requires-Dist: modal-client; extra == "deploy"
Requires-Dist: fastapi[standard]; extra == "deploy"
Requires-Dist: weaviate-client<4.0.0,>=3.26.7; extra == "deploy"
Requires-Dist: opencv-python-headless; extra == "deploy"
Requires-Dist: pillow; extra == "deploy"
Requires-Dist: torch; extra == "deploy"
Requires-Dist: torchvision; extra == "deploy"
Requires-Dist: transformers; extra == "deploy"
Requires-Dist: accelerate; extra == "deploy"
Requires-Dist: pydantic; extra == "deploy"
Requires-Dist: httpx>=0.24.0; extra == "deploy"
Provides-Extra: gpu
Requires-Dist: bitsandbytes>=0.43.1; extra == "gpu"
Provides-Extra: ml
Requires-Dist: torch>=1.11.0; extra == "ml"
Requires-Dist: transformers>=4.20.0; extra == "ml"
Dynamic: license-file
